Metadata-Version: 1.0
Name: hikjghkjhkj
Version: 0.0.1
Summary: Python REST API client for Guacamole 0.9.13 version
Home-page: https://pypi.org/manage/projects/
Author: unique
Author-email: 896035629@qq.com
License: UNKNOWN
Platform: UNKNOWN
